narasimman_text_processing_pkg/__init__.py
narasimman_text_processing_pkg/text_process.py
narasimman_text_processing-0.0.1.dist-info/LICENCE
narasimman_text_processing-0.0.1.dist-info/METADATA
narasimman_text_processing-0.0.1.dist-info/WHEEL
narasimman_text_processing-0.0.1.dist-info/top_level.txt
narasimman_text_processing-0.0.1.dist-info/RECORD
