Metadata-Version: 2.1
Name: narasimman-text-processing
Version: 0.0.1
Summary: This is the basic text processing library
Home-page: UNKNOWN
Author: Narasimman Saravana
Author-email: narasimman.saravana@gmail.com
License: UNKNOWN
Platform: UNKNOWN
Classifier: Programming Language :: Python :: 3
Classifier: License :: OSI Approved :: MIT License
Classifier: Operating System :: OS Independent
Requires-Python: >=3.6
